pytest_result_sender/__init__.py
pytest_result_sender/plugin.py
pytest_result_sender_misszhang-0.1.8.dist-info/METADATA
pytest_result_sender_misszhang-0.1.8.dist-info/WHEEL
pytest_result_sender_misszhang-0.1.8.dist-info/entry_points.txt
pytest_result_sender_misszhang-0.1.8.dist-info/RECORD
