Metadata-Version: 2.1
Name: pytest-result-sender-misszhang
Version: 0.1.8
Summary: Default template for PDM package
Author-Email: Admin <a1476088673@163.com>
License: MIT
Requires-Python: >=3.9
Requires-Dist: pytest>=8.3.5
Requires-Dist: requests>=2.32.3
